<sentence id="DrugDDI.d339.s8" origId="s8" text="Drug/ Laboratory Tests Interactions Hyperaminotransferasemia: Significant elevations of aminotransferase (SGOT [S-AST] and SGPT [S-ALT]) levels have occurred in a high percentage of patients (and healthy subjects) who have received heparin sodium."><entity id="DrugDDI.d339.s8.e0" origId="s8.p130" charOffset="0-4" type="drug" text="Drug"/><entity id="DrugDDI.d339.s8.e1" origId="s8.p134" charOffset="88-104" type="drug" text="aminotransferase"/><entity id="DrugDDI.d339.s8.e2" origId="s8.p136" charOffset="114-117" type="drug" text="AST"/><entity id="DrugDDI.d339.s8.e3" origId="s8.p138" charOffset="123-136" type="drug" text="SGPT [S-ALT]"/><entity id="DrugDDI.d339.s8.e4" origId="s8.p150" charOffset="232-246" type="drug" text="heparin sodium"/><pair id="DrugDDI.d339.s8.p0" e1="DrugDDI.d339.s8.e0" e2="DrugDDI.d339.s8.e1" interaction="false"/><pair id="DrugDDI.d339.s8.p1" e1="DrugDDI.d339.s8.e0" e2="DrugDDI.d339.s8.e2" interaction="false"/><pair id="DrugDDI.d339.s8.p2" e1="DrugDDI.d339.s8.e0" e2="DrugDDI.d339.s8.e3" interaction="false"/><pair id="DrugDDI.d339.s8.p3" e1="DrugDDI.d339.s8.e0" e2="DrugDDI.d339.s8.e4" interaction="false"/><pair id="DrugDDI.d339.s8.p4" e1="DrugDDI.d339.s8.e1" e2="DrugDDI.d339.s8.e2" interaction="false"/><pair id="DrugDDI.d339.s8.p5" e1="DrugDDI.d339.s8.e1" e2="DrugDDI.d339.s8.e3" interaction="false"/><pair id="DrugDDI.d339.s8.p6" e1="DrugDDI.d339.s8.e1" e2="DrugDDI.d339.s8.e4" interaction="false"/><pair id="DrugDDI.d339.s8.p7" e1="DrugDDI.d339.s8.e2" e2="DrugDDI.d339.s8.e3" interaction="false"/><pair id="DrugDDI.d339.s8.p8" e1="DrugDDI.d339.s8.e2" e2="DrugDDI.d339.s8.e4" interaction="false"/><pair id="DrugDDI.d339.s8.p9" e1="DrugDDI.d339.s8.e3" e2="DrugDDI.d339.s8.e4" interaction="true"/></sentence>
<sentence id="DrugDDI.d70.s3" origId="s3" text="?? ? Beta-blockers, clonidine, lithium salts, and alcohol may either potentiate or weaken the blood-glucose-lowering effect of insulin."><entity id="DrugDDI.d70.s3.e0" origId="s3.p79" charOffset="0-19" type="drug" text="Beta-blockers"/><entity id="DrugDDI.d70.s3.e1" origId="s3.p80" charOffset="20-29" type="drug" text="clonidine"/><entity id="DrugDDI.d70.s3.e2" origId="s3.p81" charOffset="31-43" type="drug" text="lithium salt"/><entity id="DrugDDI.d70.s3.e3" origId="s3.p83" charOffset="50-57" type="drug" text="alcohol"/><entity id="DrugDDI.d70.s3.e4" origId="s3.p92" charOffset="127-134" type="drug" text="insulin"/><pair id="DrugDDI.d70.s3.p0" e1="DrugDDI.d70.s3.e0" e2="DrugDDI.d70.s3.e1" interaction="false"/><pair id="DrugDDI.d70.s3.p1" e1="DrugDDI.d70.s3.e0" e2="DrugDDI.d70.s3.e2" interaction="false"/><pair id="DrugDDI.d70.s3.p2" e1="DrugDDI.d70.s3.e0" e2="DrugDDI.d70.s3.e3" interaction="false"/><pair id="DrugDDI.d70.s3.p3" e1="DrugDDI.d70.s3.e0" e2="DrugDDI.d70.s3.e4" interaction="false"/><pair id="DrugDDI.d70.s3.p4" e1="DrugDDI.d70.s3.e1" e2="DrugDDI.d70.s3.e2" interaction="false"/><pair id="DrugDDI.d70.s3.p5" e1="DrugDDI.d70.s3.e1" e2="DrugDDI.d70.s3.e3" interaction="false"/><pair id="DrugDDI.d70.s3.p6" e1="DrugDDI.d70.s3.e1" e2="DrugDDI.d70.s3.e4" interaction="false"/><pair id="DrugDDI.d70.s3.p7" e1="DrugDDI.d70.s3.e2" e2="DrugDDI.d70.s3.e3" interaction="false"/><pair id="DrugDDI.d70.s3.p8" e1="DrugDDI.d70.s3.e2" e2="DrugDDI.d70.s3.e4" interaction="false"/><pair id="DrugDDI.d70.s3.p9" e1="DrugDDI.d70.s3.e3" e2="DrugDDI.d70.s3.e4" interaction="false"/></sentence>
<sentence id="DrugDDI.d531.s10" origId="s10" text="Cimetidine Co-administration with high doses of cimetidine [800 mg twice daily] increased the Cmax of rofecoxib by 21%, the AUC0-120hr by 23% and the t1/2 by 15%."><entity id="DrugDDI.d531.s10.e0" origId="s10.p130" charOffset="0-10" type="drug" text="Cimetidine"/><entity id="DrugDDI.d531.s10.e1" origId="s10.p132" charOffset="48-64" type="drug" text="cimetidine [800"/><entity id="DrugDDI.d531.s10.e2" origId="s10.p135" charOffset="102-111" type="drug" text="rofecoxib"/><entity id="DrugDDI.d531.s10.e3" origId="s10.p140" charOffset="150-152" type="drug" text="t1"/><pair id="DrugDDI.d531.s10.p0" e1="DrugDDI.d531.s10.e0" e2="DrugDDI.d531.s10.e1" interaction="false"/><pair id="DrugDDI.d531.s10.p1" e1="DrugDDI.d531.s10.e0" e2="DrugDDI.d531.s10.e2" interaction="false"/><pair id="DrugDDI.d531.s10.p2" e1="DrugDDI.d531.s10.e0" e2="DrugDDI.d531.s10.e3" interaction="false"/><pair id="DrugDDI.d531.s10.p3" e1="DrugDDI.d531.s10.e1" e2="DrugDDI.d531.s10.e2" interaction="true"/><pair id="DrugDDI.d531.s10.p4" e1="DrugDDI.d531.s10.e1" e2="DrugDDI.d531.s10.e3" interaction="false"/><pair id="DrugDDI.d531.s10.p5" e1="DrugDDI.d531.s10.e2" e2="DrugDDI.d531.s10.e3" interaction="false"/></sentence>